Workbook
Name data_1: 'Raw Data'!$A$1:$E$77

Sheet My Money
A1: Date | B1: Cash | C1: Stocks | D1: Crypto | E1: House | F1: Debt | G1: Blocked | H1: Total | I1: Balance of the month | J1: MA 12m
A2: ='Raw Data'!A2 -> 43221 | B2: ='Raw Data'!B2 -> 15131.32 | C2: ='Raw Data'!C2 -> 2077.58 | D2: ='Raw Data'!D2 -> 3124.97 | G2: ='Raw Data'!E2 -> 1000 | H2: =IF(SUM(B2:G2)=0, "-", SUM(B2:G2)) -> 21333.87
A3: ='Raw Data'!A3 -> 43252 | B3: ='Raw Data'!B3 -> 13377.56 | C3: ='Raw Data'!C3 -> 3983.65 | D3: ='Raw Data'!D3 -> 2575.81 | G3: ='Raw Data'!E3 -> 1000 | H3: =IF(SUM(B3:G3)=0, "-", SUM(B3:G3)) -> 20937.02 | I3: =H3-H2 -> -396.85 | J3: =IF(H3="-", "-", AVERAGE(I3)) -> -396.85
A4: ='Raw Data'!A4 -> 43282 | B4: ='Raw Data'!B4 -> 9933.93 | C4: ='Raw Data'!C4 -> 9001.29 | D4: ='Raw Data'!D4 -> 2106.4 | G4: ='Raw Data'!E4 -> 1000 | H4: =IF(SUM(B4:G4)=0, "-", SUM(B4:G4)) -> 22041.62 | I4: =H4-H3 -> 1104.6 | J4: =IF(H4="-", "-", AVERAGE(I3:I4)) -> 353.875
A5: ='Raw Data'!A5 -> 43313 | B5: ='Raw Data'!B5 -> 9840.35 | C5: ='Raw Data'!C5 -> 10031.31 | D5: ='Raw Data'!D5 -> 1907.2 | G5: ='Raw Data'!E5 -> 1000 | H5: =IF(SUM(B5:G5)=0, "-", SUM(B5:G5)) -> 22778.86 | I5: =H5-H4 -> 737.24 | J5: =IF(H5="-", "-", AVERAGE(I3:I5)) -> 481.66333
A6: ='Raw Data'!A6 -> 43344 | B6: ='Raw Data'!B6 -> 11333.93 | C6: ='Raw Data'!C6 -> 10897.33 | D6: ='Raw Data'!D6 -> 1301.68 | G6: ='Raw Data'!E6 -> 1000 | H6: =IF(SUM(B6:G6)=0, "-", SUM(B6:G6)) -> 24532.94 | I6: =H6-H5 -> 1754.08 | J6: =IF(H6="-", "-", AVERAGE(I3:I6)) -> 799.7675
A7: ='Raw Data'!A7 -> 43374 | B7: ='Raw Data'!B7 -> 12109.3 | C7: ='Raw Data'!C7 -> 11666.5 | D7: ='Raw Data'!D7 -> 1085.13 | G7: ='Raw Data'!E7 -> 1000 | H7: =IF(SUM(B7:G7)=0, "-", SUM(B7:G7)) -> 25860.93 | I7: =H7-H6 -> 1327.99 | J7: =IF(H7="-", "-", AVERAGE(I3:I7)) -> 905.412
A8: ='Raw Data'!A8 -> 43405 | B8: ='Raw Data'!B8 -> 12519.97 | C8: ='Raw Data'!C8 -> 10920.72 | D8: ='Raw Data'!D8 -> 925.73 | G8: ='Raw Data'!E8 -> 1000 | H8: =IF(SUM(B8:G8)=0, "-", SUM(B8:G8)) -> 25366.42 | I8: =H8-H7 -> -494.51 | J8: =IF(H8="-", "-", AVERAGE(I3:I8)) -> 672.09167
A9: ='Raw Data'!A9 -> 43435 | B9: ='Raw Data'!B9 -> 13422.25 | C9: ='Raw Data'!C9 -> 11235.19 | D9: ='Raw Data'!D9 -> 561.57 | G9: ='Raw Data'!E9 -> 1000 | H9: =IF(SUM(B9:G9)=0, "-", SUM(B9:G9)) -> 26219.01 | I9: =H9-H8 -> 852.59 | J9: =IF(H9="-", "-", AVERAGE(I3:I9)) -> 697.87714
A10: ='Raw Data'!A10 -> 43466 | B10: ='Raw Data'!B10 -> 14488.03 | C10: ='Raw Data'!C10 -> 10174 | D10: ='Raw Data'!D10 -> 652.77 | G10: ='Raw Data'!E10 -> 1000 | H10: =IF(SUM(B10:G10)=0, "-", SUM(B10:G10)) -> 26314.8 | I10: =H10-H9 -> 95.79 | J10: =IF(H10="-", "-", AVERAGE(I3:I10)) -> 622.61625
A11: ='Raw Data'!A11 -> 43497 | B11: ='Raw Data'!B11 -> 16991.37 | C11: ='Raw Data'!C11 -> 11057.73 | D11: ='Raw Data'!D11 -> 521.11 | G11: ='Raw Data'!E11 -> 1000 | H11: =IF(SUM(B11:G11)=0, "-", SUM(B11:G11)) -> 29570.21 | I11: =H11-H10 -> 3255.41 | J11: =IF(H11="-", "-", AVERAGE(I3:I11)) -> 915.14889
A12: ='Raw Data'!A12 -> 43525 | B12: ='Raw Data'!B12 -> 14083.27 | C12: ='Raw Data'!C12 -> 15439.84 | D12: ='Raw Data'!D12 -> 629.97 | G12: ='Raw Data'!E12 -> 1000 | H12: =IF(SUM(B12:G12)=0, "-", SUM(B12:G12)) -> 31153.08 | I12: =H12-H11 -> 1582.87 | J12: =IF(H12="-", "-", AVERAGE(I3:I12)) -> 981.921
A13: ='Raw Data'!A13 -> 43556 | B13: ='Raw Data'!B13 -> 10523.69 | C13: ='Raw Data'!C13 -> 16379.9 | D13: ='Raw Data'!D13 -> 690.62 | G13: ='Raw Data'!E13 -> 2950 | H13: =IF(SUM(B13:G13)=0, "-", SUM(B13:G13)) -> 30544.21 | I13: =H13-H12 -> -608.87 | J13: =IF(H13="-", "-", AVERAGE(I3:I13)) -> 837.30364
A14: ='Raw Data'!A14 -> 43586 | B14: ='Raw Data'!B14 -> 10210.41 | C14: ='Raw Data'!C14 -> 17965.99 | D14: ='Raw Data'!D14 -> 744.52 | G14: ='Raw Data'!E14 -> 1950 | H14: =IF(SUM(B14:G14)=0, "-", SUM(B14:G14)) -> 30870.92 | I14: =H14-H13 -> 326.71 | J14: =IF(H14="-", "-", AVERAGE(I3:I14)) -> 794.75417
A15: ='Raw Data'!A15 -> 43617 | B15: ='Raw Data'!B15 -> 10177.23 | C15: ='Raw Data'!C15 -> 17930.71 | D15: ='Raw Data'!D15 -> 1234.3 | G15: ='Raw Data'!E15 -> 1950 | H15: =IF(SUM(B15:G15)=0, "-", SUM(B15:G15)) -> 31292.24 | I15: =H15-H14 -> 421.32 | J15: =IF(H15="-", "-", AVERAGE(I4:I15)) -> 862.935
A16: ='Raw Data'!A16 -> 43647 | B16: ='Raw Data'!B16 -> 12986.78 | C16: ='Raw Data'!C16 -> 18498.34 | D16: ='Raw Data'!D16 -> 1351.39 | G16: ='Raw Data'!E16 -> 1950 | H16: =IF(SUM(B16:G16)=0, "-", SUM(B16:G16)) -> 34786.51 | I16: =H16-H15 -> 3494.27 | J16: =IF(H16="-", "-", AVERAGE(I5:I16)) -> 1062.0742
A17: ='Raw Data'!A17 -> 43678 | B17: ='Raw Data'!B17 -> 13029.61 | C17: ='Raw Data'!C17 -> 19161.87 | D17: ='Raw Data'!D17 -> 1027.6 | G17: ='Raw Data'!E17 -> 1950 | H17: =IF(SUM(B17:G17)=0, "-", SUM(B17:G17)) -> 35169.08 | I17: =H17-H16 -> 382.57 | J17: =IF(H17="-", "-", AVERAGE(I6:I17)) -> 1032.5183
A18: ='Raw Data'!A18 -> 43709 | B18: ='Raw Data'!B18 -> 16327.6 | C18: ='Raw Data'!C18 -> 18629.33 | D18: ='Raw Data'!D18 -> 818.75 | G18: ='Raw Data'!E18 -> 1950 | H18: =IF(SUM(B18:G18)=0, "-", SUM(B18:G18)) -> 37725.68 | I18: =H18-H17 -> 2556.6 | J18: =IF(H18="-", "-", AVERAGE(I7:I18)) -> 1099.395
A19: ='Raw Data'!A19 -> 43739 | B19: ='Raw Data'!B19 -> 19851.43 | C19: ='Raw Data'!C19 -> 19265.21 | D19: ='Raw Data'!D19 -> 867.25 | G19: ='Raw Data'!E19 -> 1950 | H19: =IF(SUM(B19:G19)=0, "-", SUM(B19:G19)) -> 41933.89 | I19: =H19-H18 -> 4208.21 | J19: =IF(H19="-", "-", AVERAGE(I8:I19)) -> 1339.4133
A20: ='Raw Data'!A20 -> 43770 | B20: ='Raw Data'!B20 -> 18516.47 | C20: ='Raw Data'!C20 -> 19452.52 | D20: ='Raw Data'!D20 -> 872.43 | G20: ='Raw Data'!E20 -> 1950 | H20: =IF(SUM(B20:G20)=0, "-", SUM(B20:G20)) -> 40791.42 | I20: =H20-H19 -> -1142.47 | J20: =IF(H20="-", "-", AVERAGE(I9:I20)) -> 1285.4167
A21: ='Raw Data'!A21 -> 43800 | B21: ='Raw Data'!B21 -> 16942.35 | C21: ='Raw Data'!C21 -> 19827.17 | D21: ='Raw Data'!D21 -> 723.63 | G21: ='Raw Data'!E21 -> 1950 | H21: =IF(SUM(B21:G21)=0, "-", SUM(B21:G21)) -> 39443.15 | I21: =H21-H20 -> -1348.27 | J21: =IF(H21="-", "-", AVERAGE(I10:I21)) -> 1102.0117
A22: ='Raw Data'!A22 -> 43831 | B22: ='Raw Data'!B22 -> 19639.07 | C22: ='Raw Data'!C22 -> 20502.91 | D22: ='Raw Data'!D22 -> 646.71 | G22: ='Raw Data'!E22 -> 1950 | H22: =IF(SUM(B22:G22)=0, "-", SUM(B22:G22)) -> 42738.69 | I22: =H22-H21 -> 3295.54 | J22: =IF(H22="-", "-", AVERAGE(I11:I22)) -> 1368.6575
A23: ='Raw Data'!A23 -> 43862 | B23: ='Raw Data'!B23 -> 18307.38 | C23: ='Raw Data'!C23 -> 20884.81 | D23: ='Raw Data'!D23 -> 922.85 | G23: ='Raw Data'!E23 -> 1950 | H23: =IF(SUM(B23:G23)=0, "-", SUM(B23:G23)) -> 42065.04 | I23: =H23-H22 -> -673.65 | J23: =IF(H23="-", "-", AVERAGE(I12:I23)) -> 1041.2358
A24: ='Raw Data'!A24 -> 43891 | B24: ='Raw Data'!B24 -> 16198.57 | C24: ='Raw Data'!C24 -> 19034.54 | D24: ='Raw Data'!D24 -> 1091.68 | G24: ='Raw Data'!E24 -> 1950 | H24: =IF(SUM(B24:G24)=0, "-", SUM(B24:G24)) -> 38274.79 | I24: =H24-H23 -> -3790.25 | J24: =IF(H24="-", "-", AVERAGE(I13:I24)) -> 593.47583
A25: ='Raw Data'!A25 -> 43922 | B25: ='Raw Data'!B25 -> 14852.19 | C25: ='Raw Data'!C25 -> 16517.47 | D25: ='Raw Data'!D25 -> 652.86 | G25: ='Raw Data'!E25 -> 1950 | H25: =IF(SUM(B25:G25)=0, "-", SUM(B25:G25)) -> 33972.52 | I25: =H25-H24 -> -4302.27 | J25: =IF(H25="-", "-", AVERAGE(I14:I25)) -> 285.6925
... A33: ='Raw Data'!A33 -> 44166 | B33: ='Raw Data'!B33 -> 30722.53 | C33: ='Raw Data'!C33 -> 21986.26 | D33: ='Raw Data'!D33 -> 2662.39 | G33: ='Raw Data'!E33 -> 800 | H33: =IF(SUM(B33:G33)=0, "-", SUM(B33:G33)) -> 56171.18 | I33: =H33-H32 -> 4877.68 | J33: =IF(H33="-", "-", AVERAGE(I22:I33)) -> 1394.0025
A34: ='Raw Data'!A34 -> 44197 | B34: ='Raw Data'!B34 -> 33341 | C34: ='Raw Data'!C34 -> 24290.68 | D34: ='Raw Data'!D34 -> 4189.79 | G34: ='Raw Data'!E34 -> 800 | H34: =IF(SUM(B34:G34)=0, "-", SUM(B34:G34)) -> 62621.47 | I34: =IF(H34="-", "-", H34-H33) -> 6450.29 | J34: =IF(H34="-", "-", AVERAGE(I23:I34)) -> 1656.8983
A35: ='Raw Data'!A35 -> 44228 | B35: ='Raw Data'!B35 -> 33489.91 | C35: ='Raw Data'!C35 -> 25838.64 | D35: ='Raw Data'!D35 -> 6618.56 | G35: ='Raw Data'!E35 -> 800 | H35: =IF(SUM(B35:G35)=0, "-", SUM(B35:G35)) -> 66747.11 | I35: =IF(H35="-", "-", H35-H34) -> 4125.64 | J35: =IF(H35="-", "-", AVERAGE(I24:I35)) -> 2056.8392
A36: ='Raw Data'!A36 -> 44256 | B36: ='Raw Data'!B36 -> 33619.05 | C36: ='Raw Data'!C36 -> 27125.83 | D36: ='Raw Data'!D36 -> 7768.4 | G36: ='Raw Data'!E36 -> 800 | H36: =IF(SUM(B36:G36)=0, "-", SUM(B36:G36)) -> 69313.28 | I36: =IF(H36="-", "-", H36-H35) -> 2566.17 | J36: =IF(H36="-", "-", AVERAGE(I25:I36)) -> 2586.5408
A37: ='Raw Data'!A37 -> 44287 | B37: ='Raw Data'!B37 -> 35580.63 | C37: ='Raw Data'!C37 -> 28640.63 | D37: ='Raw Data'!D37 -> 7951.38 | G37: ='Raw Data'!E37 -> 0 | H37: =IF(SUM(B37:G37)=0, "-", SUM(B37:G37)) -> 72172.64 | I37: =IF(H37="-", "-", H37-H36) -> 2859.36 | J37: =IF(H37="-", "-", AVERAGE(I26:I37)) -> 3183.3433
A38: ='Raw Data'!A38 -> 44317 | B38: ='Raw Data'!B38 -> 35393.24 | C38: ='Raw Data'!C38 -> 31297.42 | D38: ='Raw Data'!D38 -> 8054.46 | G38: ='Raw Data'!E38 -> 0 | H38: =IF(SUM(B38:G38)=0, "-", SUM(B38:G38)) -> 74745.12 | I38: =IF(H38="-", "-", H38-H37) -> 2572.48 | J38: =IF(H38="-", "-", AVERAGE(I27:I38)) -> 3067.1467
A39: ='Raw Data'!A39 -> 44348 | B39: ='Raw Data'!B39 -> 36400.32 | C39: ='Raw Data'!C39 -> 31333.49 | D39: ='Raw Data'!D39 -> 7828.05 | G39: ='Raw Data'!E39 -> 300 | H39: =IF(SUM(B39:G39)=0, "-", SUM(B39:G39)) -> 75861.86 | I39: =IF(H39="-", "-", H39-H38) -> 1116.74 | J39: =IF(H39="-", "-", AVERAGE(I28:I39)) -> 2975.6525
A40: ='Raw Data'!A40 -> 44378 | B40: ='Raw Data'!B40 -> 36650.94 | C40: ='Raw Data'!C40 -> 33619.72 | D40: ='Raw Data'!D40 -> 7822.14 | G40: ='Raw Data'!E40 -> 300 | H40: =IF(SUM(B40:G40)=0, "-", SUM(B40:G40)) -> 78392.8 | I40: =IF(H40="-", "-", H40-H39) -> 2530.94 | J40: =IF(H40="-", "-", AVERAGE(I29:I40)) -> 3171.5583
A41: ='Raw Data'!A41 -> 44409 | B41: ='Raw Data'!B41 -> 36662.85 | C41: ='Raw Data'!C41 -> 35460.7 | D41: ='Raw Data'!D41 -> 9142.64 | G41: ='Raw Data'!E41 -> 300 | H41: =IF(SUM(B41:G41)=0, "-", SUM(B41:G41)) -> 81566.19 | I41: =IF(H41="-", "-", H41-H40) -> 3173.39 | J41: =IF(H41="-", "-", AVERAGE(I30:I41)) -> 2842.3617
A42: ='Raw Data'!A42 -> 44440 | B42: ='Raw Data'!B42 -> 35386.16 | C42: ='Raw Data'!C42 -> 37363.68 | D42: ='Raw Data'!D42 -> 9802.58 | G42: ='Raw Data'!E42 -> 300 | H42: =IF(SUM(B42:G42)=0, "-", SUM(B42:G42)) -> 82852.42 | I42: =IF(H42="-", "-", H42-H41) -> 1286.23 | J42: =IF(H42="-", "-", AVERAGE(I31:I42)) -> 2749.1842
A43: ='Raw Data'!A43 -> 44470 | B43: ='Raw Data'!B43 -> 33341.8 | C43: ='Raw Data'!C43 -> 38977.43 | D43: ='Raw Data'!D43 -> 9373.07 | G43: ='Raw Data'!E43 -> 300 | H43: =IF(SUM(B43:G43)=0, "-", SUM(B43:G43)) -> 81992.3 | I43: =IF(H43="-", "-", H43-H42) -> -860.12 | J43: =IF(H43="-", "-", AVERAGE(I32:I43)) -> 2610.1225
A44: ='Raw Data'!A44 -> 44507 | B44: ='Raw Data'!B44 -> 31235.23 | C44: ='Raw Data'!C44 -> 43751.77 | D44: ='Raw Data'!D44 -> 10588.52 | G44: ='Raw Data'!E44 -> 300 | H44: =IF(SUM(B44:G44)=0, "-", SUM(B44:G44)) -> 85875.52 | I44: =IF(H44="-", "-", H44-H43) -> 3883.22 | J44: =IF(H44="-", "-", AVERAGE(I33:I44)) -> 2881.835
A45: ='Raw Data'!A45 -> 44532 | B45: ='Raw Data'!B45 -> 30031.4 | C45: ='Raw Data'!C45 -> 44193.46 | D45: ='Raw Data'!D45 -> 9751.38 | G45: ='Raw Data'!E45 -> 300 | H45: =IF(SUM(B45:G45)=0, "-", SUM(B45:G45)) -> 84276.24 | I45: =IF(H45="-", "-", H45-H44) -> -1599.28 | J45: =IF(H45="-", "-", AVERAGE(I34:I45)) -> 2342.0883
... A60: ='Raw Data'!A60 -> 44986 | B60: ='Raw Data'!B60 -> 37022.63 | C60: ='Raw Data'!C60 -> 58416.19 | D60: ='Raw Data'!D60 -> 12062.52 | G60: ='Raw Data'!E60 -> 300 | H60: =IF(SUM(B60:G60)=0, "-", SUM(B60:G60)) -> 107801.34 | I60: =IF(H60="-", "-", H60-H59) -> 2280.73 | J60: =IF(H60="-", "-", AVERAGE(I49:I60)) -> 1486.4375
A61: ='Raw Data'!A61 -> 45017 | B61: ='Raw Data'!B61 -> 10740.43 | C61: ='Raw Data'!C61 -> 58939.75 | D61: ='Raw Data'!D61 -> 12903.8 | E61: 175000 | F61: -155000 | G61: ='Raw Data'!E61 -> 300 | H61: =IF(SUM(B61:G61)=0, "-", SUM(B61:G61)) -> 102883.98 | I61: =IF(H61="-", "-", H61-H60) -> -4917.36 | J61: =IF(H61="-", "-", AVERAGE(I50:I61)) -> 710.615
A62: ='Raw Data'!A62 -> 45049 | B62: ='Raw Data'!B62 -> 15554.44 | C62: ='Raw Data'!C62 -> 59613.96 | D62: ='Raw Data'!D62 -> 12836.66 | E62: 175000 | F62: -155000 | G62: ='Raw Data'!E62 -> 300 | H62: =IF(SUM(B62:G62)=0, "-", SUM(B62:G62)) -> 108305.06 | I62: =IF(H62="-", "-", H62-H61) -> 5421.08 | J62: =IF(H62="-", "-", AVERAGE(I51:I62)) -> 1265.145
A63: ='Raw Data'!A63 -> 45079 | B63: ='Raw Data'!B63 -> 16414.13 | C63: ='Raw Data'!C63 -> 61782.62 | D63: ='Raw Data'!D63 -> 12480.7 | E63: 175000 | F63: -155000 | G63: ='Raw Data'!E63 -> 0 | H63: =IF(SUM(B63:G63)=0, "-", SUM(B63:G63)) -> 110677.45 | I63: =IF(H63="-", "-", H63-H62) -> 2372.39 | J63: =IF(H63="-", "-", AVERAGE(I52:I63)) -> 1496.9092
A64: ='Raw Data'!A64 -> 45111 | B64: ='Raw Data'!B64 -> 17425.8 | C64: ='Raw Data'!C64 -> 65401.28 | D64: ='Raw Data'!D64 -> 13644.72 | E64: 175000 | F64: -155000 | G64: ='Raw Data'!E64 -> 0 | H64: =IF(SUM(B64:G64)=0, "-", SUM(B64:G64)) -> 116471.8 | I64: =IF(H64="-", "-", H64-H63) -> 5794.35 | J64: =IF(H64="-", "-", AVERAGE(I53:I64)) -> 2150.4558
A65: ='Raw Data'!A65 -> 45141 | B65: ='Raw Data'!B65 -> 18791.73 | C65: ='Raw Data'!C65 -> 67098.1 | D65: ='Raw Data'!D65 -> 13307.38 | E65: 175000 | F65: -155000 | G65: ='Raw Data'!E65 -> 0 | H65: =IF(SUM(B65:G65)=0, "-", SUM(B65:G65)) -> 119197.21 | I65: =IF(H65="-", "-", H65-H64) -> 2725.41 | J65: =IF(H65="-", "-", AVERAGE(I54:I65)) -> 1718.4542
A66: ='Raw Data'!A66 -> 45171 | B66: ='Raw Data'!B66 -> 18662.22 | C66: ='Raw Data'!C66 -> 68443.44 | D66: ='Raw Data'!D66 -> 12524.72 | E66: 175000 | F66: -155000 | G66: ='Raw Data'!E66 -> 0 | H66: =IF(SUM(B66:G66)=0, "-", SUM(B66:G66)) -> 119630.38 | I66: =IF(H66="-", "-", H66-H65) -> 433.17 | J66: =IF(H66="-", "-", AVERAGE(I55:I66)) -> 1811.9575
A67: ='Raw Data'!A67 -> 45202 | B67: ='Raw Data'!B67 -> 19339.84 | C67: ='Raw Data'!C67 -> 68483.18 | D67: ='Raw Data'!D67 -> 13117.39 | E67: 175000 | F67: -155000 | G67: ='Raw Data'!E67 -> 0 | H67: =IF(SUM(B67:G67)=0, "-", SUM(B67:G67)) -> 120940.41 | I67: =IF(H67="-", "-", H67-H66) -> 1310.03 | J67: =IF(H67="-", "-", AVERAGE(I56:I67)) -> 2105.5308
A68: ='Raw Data'!A68 -> 45233 | B68: ='Raw Data'!B68 -> 18573.8 | C68: ='Raw Data'!C68 -> 69131.03 | D68: ='Raw Data'!D68 -> 14925.8 | E68: 175000 | F68: -155000 | G68: ='Raw Data'!E68 -> 0 | H68: =IF(SUM(B68:G68)=0, "-", SUM(B68:G68)) -> 122630.63 | I68: =IF(H68="-", "-", H68-H67) -> 1690.22 | J68: =IF(H68="-", "-", AVERAGE(I57:I68)) -> 1894.345
A69: ='Raw Data'!A69 -> 45269 | B69: ='Raw Data'!B69 -> 18598.18 | C69: ='Raw Data'!C69 -> 72604.42 | D69: ='Raw Data'!D69 -> 17437 | E69: 175000 | F69: -155000 | G69: ='Raw Data'!E69 -> 0 | H69: =IF(SUM(B69:G69)=0, "-", SUM(B69:G69)) -> 128639.6 | I69: =IF(H69="-", "-", H69-H68) -> 6008.97 | J69: =IF(H69="-", "-", AVERAGE(I58:I69)) -> 2457.3917
A70: ='Raw Data'!A70 -> 45294 | B70: ='Raw Data'!B70 -> 14316.1 | C70: ='Raw Data'!C70 -> 74137.07 | D70: ='Raw Data'!D70 -> 17727.48 | E70: 175000 | F70: =-155000+8500 -> -146500 | G70: ='Raw Data'!E70 -> 0 | H70: =IF(SUM(B70:G70)=0, "-", SUM(B70:G70)) -> 134680.65 | I70: =IF(H70="-", "-", H70-H69) -> 6041.05 | J70: =IF(H70="-", "-", AVERAGE(I59:I70)) -> 2857.445
A71: ='Raw Data'!A71 -> 45324 | B71: ='Raw Data'!B71 -> 13224.63 | C71: ='Raw Data'!C71 -> 78800.98 | D71: ='Raw Data'!D71 -> 17103.31 | E71: 175000 | F71: =-155000+8500 -> -146500 | G71: ='Raw Data'!E71 -> 0 | H71: =IF(SUM(B71:G71)=0, "-", SUM(B71:G71)) -> 137628.92 | I71: =IF(H71="-", "-", H71-H70) -> 2948.27 | J71: =IF(H71="-", "-", AVERAGE(I60:I71)) -> 2675.6925
A72: ='Raw Data'!A72 -> 45353 | B72: ='Raw Data'!B72 -> 12591.02 | C72: ='Raw Data'!C72 -> 83711.03 | D72: ='Raw Data'!D72 -> 22549.61 | E72: 175000 | F72: =-155000+8500 -> -146500 | G72: ='Raw Data'!E72 -> 0 | H72: =IF(SUM(B72:G72)=0, "-", SUM(B72:G72)) -> 147351.66 | I72: =IF(H72="-", "-", H72-H71) -> 9722.74 | J72: =IF(H72="-", "-", AVERAGE(I61:I72)) -> 3295.86
A73: ='Raw Data'!A73 -> 45385 | B73: ='Raw Data'!B73 -> 14241.76 | C73: ='Raw Data'!C73 -> 87179.59 | D73: ='Raw Data'!D73 -> 23486.85 | E73: 175000 | F73: =-155000+8500 -> -146500 | G73: ='Raw Data'!E77 -> 0 | H73: =IF(SUM(B73:G73)=0, "-", SUM(B73:G73)) -> 153408.2 | I73: =IF(H73="-", "-", H73-H72) -> 6056.54 | J73: =IF(H73="-", "-", AVERAGE(I62:I73)) -> 4210.3517
A74: ='Raw Data'!A74 -> 45416 | B74: ='Raw Data'!B74 -> 14245.14 | C74: ='Raw Data'!C74 -> 87323.9 | D74: ='Raw Data'!D74 -> 22158.26 | E74: 175000 | F74: =-155000+8500 -> -146500 | G74: ='Raw Data'!E78 -> 0 | H74: =IF(SUM(B74:G74)=0, "-", SUM(B74:G74)) -> 152227.3 | I74: =IF(H74="-", "-", H74-H73) -> -1180.9 | J74: =IF(H74="-", "-", AVERAGE(I63:I74)) -> 3660.1867
A75: ='Raw Data'!A75 -> 45444 | B75: ='Raw Data'!B75 -> 15783.57 | C75: ='Raw Data'!C75 -> 89151.48 | D75: ='Raw Data'!D75 -> 23782.86 | E75: 175000 | F75: =-155000+8500 -> -146500 | G75: ='Raw Data'!E79 -> 0 | H75: =IF(SUM(B75:G75)=0, "-", SUM(B75:G75)) -> 157217.91 | I75: =IF(H75="-", "-", H75-H74) -> 4990.61 | J75: =IF(H75="-", "-", AVERAGE(I64:I75)) -> 3878.3717
A76: ='Raw Data'!A76 -> 45476 | B76: ='Raw Data'!B76 -> 15718.35 | C76: ='Raw Data'!C76 -> 95159.42 | D76: ='Raw Data'!D76 -> 20918.77 | E76: 175000 | F76: =-155000+8500 -> -146500 | G76: ='Raw Data'!E80 -> 0 | H76: =IF(SUM(B76:G76)=0, "-", SUM(B76:G76)) -> 160296.54 | I76: =IF(H76="-", "-", H76-H75) -> 3078.63 | J76: =IF(H76="-", "-", AVERAGE(I65:I76)) -> 3652.0617
A77: ='Raw Data'!A77 -> 45505 | B77: ='Raw Data'!B77 -> 16555.97 | C77: ='Raw Data'!C77 -> 98330.91 | D77: ='Raw Data'!D77 -> 22283.79 | E77: 175000 | F77: =-155000+8500 -> -146500 | G77: ='Raw Data'!E81 -> 0 | H77: =IF(SUM(B77:G77)=0, "-", SUM(B77:G77)) -> 165670.67 | I77: =IF(H77="-", "-", H77-H76) -> 5374.13 | J77: =IF(H77="-", "-", AVERAGE(I66:I77)) -> 3872.7883
A78: ='Raw Data'!A78 -> 0 | B78: ='Raw Data'!B78 -> 0 | C78: ='Raw Data'!C78 -> 0 | D78: ='Raw Data'!D78 -> 0 | G78: ='Raw Data'!E82 -> 0 | H78: =IF(SUM(B78:G78)=0, "-", SUM(B78:G78)) -> - | I78: =IF(H78="-", "-", H78-H77) -> - | J78: =IF(H78="-", "-", AVERAGE(I67:I78)) -> -
A79: ='Raw Data'!A79 -> 0 | B79: ='Raw Data'!B79 -> 0 | C79: ='Raw Data'!C79 -> 0 | D79: ='Raw Data'!D79 -> 0 | G79: ='Raw Data'!E83 -> 0 | H79: =IF(SUM(B79:G79)=0, "-", SUM(B79:G79)) -> - | I79: =IF(H79="-", "-", H79-H78) -> - | J79: =IF(H79="-", "-", AVERAGE(I68:I79)) -> -
A80: ='Raw Data'!A80 -> 0 | B80: ='Raw Data'!B80 -> 0 | C80: ='Raw Data'!C80 -> 0 | D80: ='Raw Data'!D80 -> 0 | G80: ='Raw Data'!E84 -> 0 | H80: =IF(SUM(B80:G80)=0, "-", SUM(B80:G80)) -> - | I80: =IF(H80="-", "-", H80-H79) -> - | J80: =IF(H80="-", "-", AVERAGE(I69:I80)) -> -

Sheet Chart

Sheet Year Summary
A1: Year | B1: Forecast | C1: Total | D1: Change since last year
A2: =YEAR('Raw Data'!A10)-1 -> 2018 | C2: ='My Money'!H10 -> 26314.8 | D2: =C2-Tabla3[[#This Row],[Total]] -> 4980.93
A3: =A2+1 -> 2019 | B3: =FORECAST('My Money'!A22,'My Money'!H2:H9,'My Money'!A2:A9) -> 37239.503 | C3: ='My Money'!H22 -> 42738.69 | D3: =C3-C2 -> 16423.89
A4: =A3+1 -> 2020 | B4: =C3+D3 -> 59162.58 | C4: ='My Money'!H34 -> 62621.47 | D4: =C4-C3 -> 19882.78
A5: =A4+1 -> 2021 | B5: =C4+D4 -> 82504.25 | C5: ='My Money'!H46 -> 91258.07 | D5: =C5-C4 -> 28636.6
A6: =A5+1 -> 2022 | B6: =C5+D5 -> 119894.67 | C6: ='My Money'!H58 -> 100391.31 | D6: =C6-C5 -> 9133.24
A7: 2023 | B7: =C6+D6 -> 109524.55 | C7: ='My Money'!H70 -> 134680.65 | D7: =C7-C6 -> 34289.34
A8: 2024 | B8: =C7+D7 -> 168969.99 | C8: ='My Money'!H82 -> 0 | D8: =C8-C7 -> -134680.65

Sheet Metadata
A1: ='My Money'!B1 -> Cash | B1: ='Raw Data'!B1 -> Cash | C1: {=LOOKUP(2,1/('Raw Data'!B:B<>""),'Raw Data'!B:B)} -> 16555.97
A2: ='My Money'!C1 -> Stocks | B2: ='Raw Data'!C1 -> Stocks | C2: {=LOOKUP(2,1/('Raw Data'!C:C<>""),'Raw Data'!C:C)} -> 98330.91
A3: ='My Money'!D1 -> Crypto | B3: ='Raw Data'!D1 -> Crypto | C3: {=LOOKUP(2,1/('Raw Data'!D:D<>""),'Raw Data'!D:D)} -> 22283.79
A4: ='My Money'!G1 -> Blocked | B4: ='Raw Data'!E1 -> Blocked | C4: {=LOOKUP(2,1/('Raw Data'!E:E<>""),'Raw Data'!E:E)} -> 0
A8: ='My Money'!H1 -> Total | C8: {=LOOKUP(2,1/('My Money'!H:H<>"")/('My Money'!H:H<>"-"),'My Money'!H:H)} -> 165670.67

Sheet Raw Data
A1: Date | B1: Cash | C1: Stocks | D1: Crypto | E1: Blocked
A2: 43221 | B2: 15131.32 | C2: 2077.58 | D2: 3124.97 | E2: 1000
A3: 43252 | B3: 13377.56 | C3: 3983.65 | D3: 2575.81 | E3: 1000
A4: 43282 | B4: 9933.93 | C4: 9001.29 | D4: 2106.4 | E4: 1000
A5: 43313 | B5: 9840.35 | C5: 10031.31 | D5: 1907.2 | E5: 1000
A6: 43344 | B6: 11333.93 | C6: 10897.33 | D6: 1301.68 | E6: 1000
A7: 43374 | B7: 12109.3 | C7: 11666.5 | D7: 1085.13 | E7: 1000
A8: 43405 | B8: 12519.97 | C8: 10920.72 | D8: 925.73 | E8: 1000
A9: 43435 | B9: 13422.25 | C9: 11235.19 | D9: 561.57 | E9: 1000
A10: 43466 | B10: 14488.03 | C10: 10174 | D10: 652.77 | E10: 1000
A11: 43497 | B11: 16991.37 | C11: 11057.73 | D11: 521.11 | E11: 1000
A12: 43525 | B12: 14083.27 | C12: 15439.84 | D12: 629.97 | E12: 1000
A13: 43556 | B13: 10523.69 | C13: 16379.9 | D13: 690.62 | E13: 2950
... A77: 45505 | B77: 16555.97 | C77: 98330.91 | D77: 22283.79 | E77: 0
